tls/__init__.py
django_tls_rvanlaar-0.0.3.dist-info/LICENSE
django_tls_rvanlaar-0.0.3.dist-info/METADATA
django_tls_rvanlaar-0.0.3.dist-info/WHEEL
django_tls_rvanlaar-0.0.3.dist-info/top_level.txt
django_tls_rvanlaar-0.0.3.dist-info/RECORD
