Metadata-Version: 2.1
Name: django-tls-rvanlaar
Version: 0.0.3
Summary: Stores the current request in Thread Local Storage using Werkzeug
Home-page: https://github.com/rvanlaar/django-tls
Author: Roland van Laar
Author-email: roland@rolandvanlaar.nl
License: BSD
Platform: UNKNOWN
Classifier: Development Status :: 3 - Alpha
Classifier: Environment :: Web Environment
Classifier: Intended Audience :: Developers
Classifier: License :: OSI Approved :: BSD License
Classifier: Operating System :: OS Independent
Classifier: Programming Language :: Python
Classifier: Topic :: Internet :: WWW/HTTP :: Dynamic Content
Classifier: Framework :: Django
Requires-Dist: Werkzeug (>=0.6.2)
